pumpkin_solver-0.2.2.dist-info/METADATA
pumpkin_solver-0.2.2.dist-info/WHEEL
pumpkin_solver/__init__.py
pumpkin_solver/pumpkin_solver.cpython-312-darwin.so
pumpkin_solver-0.2.2.dist-info/RECORD
